pytio/_Tio.py
pytio/_TioFile.py
pytio/_TioRequest.py
pytio/_TioResponse.py
pytio/_TioResult.py
pytio/_TioVariable.py
pytio/__init__.py
pytio-0.3.1.dist-info/DESCRIPTION.rst
pytio-0.3.1.dist-info/METADATA
pytio-0.3.1.dist-info/RECORD
pytio-0.3.1.dist-info/WHEEL
pytio-0.3.1.dist-info/metadata.json
pytio-0.3.1.dist-info/top_level.txt
